README.rst
setup.py
app/__init__.py
app/assets.py
app/decorators.py
app/email.py
app/utils.py
app/account/__init__.py
app/account/forms.py
app/account/views.py
app/admin/__init__.py
app/admin/forms.py
app/admin/views.py
app/main/__init__.py
app/main/errors.py
app/main/forms.py
app/main/views.py
app/models/__init__.py
app/models/miscellaneous.py
app/models/user.py
flask_base.egg-info/PKG-INFO
flask_base.egg-info/SOURCES.txt
flask_base.egg-info/dependency_links.txt
flask_base.egg-info/not-zip-safe
flask_base.egg-info/requires.txt
flask_base.egg-info/top_level.txt