Metadata-Version: 1.2
Name: flask-base
Version: 0.0.2
Summary: A simple Flask boilerplate app with SQLAlchemy, Redis, User Authentication, and more.
Home-page: https://github.com/longniao/flask-base
Author: Longniao
Author-email: longniao@gmail.com
Maintainer: Longniao
Maintainer-email: longniao@gmail.com
License: MIT
Keywords: flask-base flask
Platform: any
Classifier: Development Status :: 5 - Production/Stable
Classifier: Environment :: Console
Classifier: Intended Audience :: Developers
Classifier: License :: OSI Approved :: MIT License
Classifier: Operating System :: OS Independent
Classifier: Programming Language :: Python
Classifier: Programming Language :: Python :: 3.5
Classifier: Programming Language :: Python :: 3.6
Classifier: Programming Language :: Python :: 3.7
Requires-Python: >=3.5
